ome_zarr/__init__.py
ome_zarr/_version.py
ome_zarr/axes.py
ome_zarr/cli.py
ome_zarr/conversions.py
ome_zarr/csv.py
ome_zarr/dask_utils.py
ome_zarr/data.py
ome_zarr/format.py
ome_zarr/io.py
ome_zarr/reader.py
ome_zarr/scale.py
ome_zarr/types.py
ome_zarr/utils.py
ome_zarr/writer.py
ome_zarr-0.12.2.dist-info/licenses/LICENSE
ome_zarr-0.12.2.dist-info/METADATA
ome_zarr-0.12.2.dist-info/WHEEL
ome_zarr-0.12.2.dist-info/entry_points.txt
ome_zarr-0.12.2.dist-info/top_level.txt
ome_zarr-0.12.2.dist-info/RECORD
