Metadata-Version: 2.4
Name: ome-zarr
Version: 0.12.2
Summary: Implementation of images in Zarr files.
Author: The Open Microscopy Team
License-Expression: BSD-2-Clause
Project-URL: Documentation, https://ome-zarr.readthedocs.io
Project-URL: Repository, https://github.com/ome/ome-zarr-py
Project-URL: Changelog, https://github.com/ome/ome-zarr-py/blob/master/CHANGELOG.md
Classifier: Development Status :: 4 - Beta
Classifier: Intended Audience :: Developers
Classifier: Intended Audience :: Science/Research
Classifier: Topic :: Software Development :: Libraries :: Python Modules
Classifier: Programming Language :: Python
Classifier: Programming Language :: Python :: 3
Classifier: Operating System :: OS Independent
Requires-Python: >3.10
License-File: LICENSE
Requires-Dist: numpy
Requires-Dist: dask
Requires-Dist: zarr>=v3.0.0
Requires-Dist: fsspec[s3]!=2021.07.0,!=2023.9.0,>=0.8
Requires-Dist: aiohttp
Requires-Dist: requests
Requires-Dist: scikit-image>=0.19.0
Requires-Dist: toolz
Provides-Extra: tests
Requires-Dist: pytest; extra == "tests"
Dynamic: license-file
